README.md
setup.cfg
setup.py
datahandler_Atishay_101703121/__init__.py
datahandler_Atishay_101703121/basic.py
datahandler_Atishay_101703121/datahandler.py
datahandler_Atishay_101703121.egg-info/PKG-INFO
datahandler_Atishay_101703121.egg-info/SOURCES.txt
datahandler_Atishay_101703121.egg-info/dependency_links.txt
datahandler_Atishay_101703121.egg-info/top_level.txt