Metadata-Version: 2.1
Name: datahandler-Atishay-101703121
Version: 0.1
Summary: Handling Missing values in a given data set and imputing them.
Home-page: UNKNOWN
Author: atishay_123
Author-email: atishay21@gmail.com
License: UNKNOWN
Platform: UNKNOWN
Classifier: Programming Language :: Python :: 3
Classifier: License :: OSI Approved :: MIT License
Classifier: Operating System :: OS Independent
Requires-Python: >=3.6
